smart_keyframe_extractor/__init__.py
smart_keyframe_extractor/azure_openai.py
smart_keyframe_extractor/cli.py
smart_keyframe_extractor/extractor.py
smart_keyframe_extractor/vision_utils.py
smart_keyframe_extractor-0.1.0.dist-info/licenses/LICENSE
smart_keyframe_extractor-0.1.0.dist-info/METADATA
smart_keyframe_extractor-0.1.0.dist-info/WHEEL
smart_keyframe_extractor-0.1.0.dist-info/entry_points.txt
smart_keyframe_extractor-0.1.0.dist-info/top_level.txt
smart_keyframe_extractor-0.1.0.dist-info/RECORD
