Metadata-Version: 2.4
Name: smart-keyframe-extractor
Version: 0.1.0
Summary: 智能视频关键帧提取工具，支持自适应模式、分辨率选择和Azure OpenAI分析
Author-email: cjj198909 <cjj198909@gmail.com>
License-Expression: MIT
Project-URL: Homepage, https://github.com/cjj198909/smart-keyframe-extractor
Project-URL: Repository, https://github.com/cjj198909/smart-keyframe-extractor
Project-URL: Documentation, https://github.com/cjj198909/smart-keyframe-extractor/blob/main/README.md
Project-URL: Bug Tracker, https://github.com/cjj198909/smart-keyframe-extractor/issues
Keywords: video,keyframe,extraction,computer-vision,azure,openai,ai-analysis
Classifier: Development Status :: 4 - Beta
Classifier: Intended Audience :: Developers
Classifier: Intended Audience :: Science/Research
Classifier: Operating System :: OS Independent
Classifier: Programming Language :: Python :: 3
Classifier: Programming Language :: Python :: 3.8
Classifier: Programming Language :: Python :: 3.9
Classifier: Programming Language :: Python :: 3.10
Classifier: Programming Language :: Python :: 3.11
Classifier: Programming Language :: Python :: 3.12
Classifier: Topic :: Scientific/Engineering :: Artificial Intelligence
Classifier: Topic :: Software Development :: Libraries :: Python Modules
Classifier: Topic :: Multimedia :: Video
Requires-Python: >=3.8
License-File: LICENSE
Requires-Dist: opencv-python>=4.5.0
Requires-Dist: Pillow>=8.0.0
Requires-Dist: numpy>=1.19.0
Requires-Dist: requests>=2.25.0
Provides-Extra: azure
Requires-Dist: openai>=1.0.0; extra == "azure"
Provides-Extra: dev
Requires-Dist: pytest>=6.0; extra == "dev"
Requires-Dist: pytest-cov>=2.0; extra == "dev"
Requires-Dist: black>=21.0; extra == "dev"
Requires-Dist: isort>=5.0; extra == "dev"
Requires-Dist: flake8>=3.8; extra == "dev"
Requires-Dist: mypy>=0.910; extra == "dev"
Provides-Extra: all
Requires-Dist: openai>=1.0.0; extra == "all"
Requires-Dist: pytest>=6.0; extra == "all"
Requires-Dist: pytest-cov>=2.0; extra == "all"
Requires-Dist: black>=21.0; extra == "all"
Requires-Dist: isort>=5.0; extra == "all"
Requires-Dist: flake8>=3.8; extra == "all"
Requires-Dist: mypy>=0.910; extra == "all"
Dynamic: license-file
